{
    "style_1": {
        "top": {
            "image": "image100.jpg",
            "type": "Shirts",
            "gender": "Men",
            "color": "lightgray",
            "season": "Summer",
            "style": "Casual"
        },
        "bottom": {
            "image": "image102.jpg",
            "type": "Casual Shoes",
            "gender": "Men",
            "color": "darkslategray",
            "season": "Summer",
            "style": "Casual"
        },
        "shoes": {
            "image": "image135.jpg",
            "type": "Sports Shoes",
            "gender": "Men",
            "color": "black",
            "season": "Summer",
            "style": "Sports"
        }
    },
    "style_2": {
        "top": {
            "image": "image101.jpeg",
            "type": "Shirts",
            "gender": "Men",
            "color": "slategrey",
            "season": "Summer",
            "style": "Casual"
        },
        "bottom": {
            "image": "image109.jpg",
            "type": "Track Pants",
            "gender": "Men",
            "color": "black",
            "season": "Summer",
            "style": "Casual"
        },
        "shoes": {
            "image": "image138.jpg",
            "type": "Formal Shoes",
            "gender": "Men",
            "color": "black",
            "season": "Summer",
            "style": "Formal"
        }
    },
    "style_3": {
        "top": {
            "image": "image136.jpg",
            "type": "Shirts",
            "gender": "Men",
            "color": "darkgrey",
            "season": "Summer",
            "style": "Casual"
        },
        "bottom": {
            "image": "image115.jpg",
            "type": "Track Pants",
            "gender": "Men",
            "color": "darkslategray",
            "season": "Summer",
            "style": "Ethnic"
        },
        "shoes": {
            "image": "image116.jpg",
            "type": "Sports Shoes",
            "gender": "Men",
            "color": "black",
            "season": "Summer",
            "style": "Casual"
        }
    },
    "style_4": {
        "top": {
            "image": "image146.jpg",
            "type": "Shirts",
            "gender": "Men",
            "color": "lightgray",
            "season": "Summer",
            "style": "Casual"
        },
        "bottom": {
            "image": "image108.jpg",
            "type": "Track Pants",
            "gender": "Men",
            "color": "darkslategray",
            "season": "Summer",
            "style": "Casual"
        },
        "shoes": {
            "image": "image141.jpg",
            "type": "Casual Shoes",
            "gender": "Men",
            "color": "lavender",
            "season": "Summer",
            "style": "Casual"
        }
    }
}